paylink_tracing/__init__.py
paylink_tracing/config.py
paylink_tracing/db.py
paylink_tracing/trace.py
paylink_tracing-0.1.0.dist-info/METADATA
paylink_tracing-0.1.0.dist-info/WHEEL
paylink_tracing-0.1.0.dist-info/RECORD
